<?xml version="1.0"?>
<registry xmlns:i18n="http://xml.zope.org/namespaces/i18n"
          i18n:domain="bda.plone.ajax">

  <!-- create a bundle definition -->
  <records prefix="plone.bundles/bdajax-bundle"
            interface='Products.CMFPlone.interfaces.IBundleRegistry'>
    <value key="enabled">True</value>
    <value key="jscompilation">++resource++bdajax/bdajax.js</value>
    <value key="csscompilation">++resource++bdajax/bdajax.css</value>
    <value key="last_compilation">2016-02-28 00:00:00</value>
  </records>

</registry>
